{
    "atoms": [
        { "element": "Ag", "location": [ -9.305699, -9.143219, -4.359913 ] },
        { "element": "Ag", "location": [ -6.416319, -9.143219, -4.359913 ] },
        { "element": "Ag", "location": [ -3.526939, -9.143219, -4.359913 ] },
        { "element": "Ag", "location": [ -0.637560, -9.143219, -4.359913 ] },
        { "element": "Ag", "location": [ 2.251820, -9.143219, -4.359913 ] },
        { "element": "Ag", "location": [ 5.141200, -9.143219, -4.359913 ] },
        { "element": "Ag", "location": [ 8.030580, -9.143219, -4.359913 ] },
        { "element": "Ag", "location": [ 10.919959, -9.143219, -4.359913 ] },
        { "element": "Ag", "location": [ -9.305699, -6.253839, -4.359913 ] },
        { "element": "Ag", "location": [ -6.416319, -6.253839, -4.359913 ] },
        { "element": "Ag", "location": [ -3.526939, -6.253839, -4.359913 ] },
        { "element": "Ag", "location": [ -0.637560, -6.253839, -4.359913 ] },
        { "element": "Ag", "location": [ 2.251820, -6.253839, -4.359913 ] },
        { "element": "Ag", "location": [ 5.141200, -6.253839, -4.359913 ] },
        { "element": "Ag", "location": [ 8.030580, -6.253839, -4.359913 ] },
        { "element": "Ag", "location": [ 10.919959, -6.253839, -4.359913 ] },
        { "element": "Ag", "location": [ -9.305699, -3.364460, -4.359913 ] },
        { "element": "Ag", "location": [ -6.416319, -3.364460, -4.359913 ] },
        { "element": "Ag", "location": [ -3.526939, -3.364460, -4.359913 ] },
        { "element": "Ag", "location": [ -0.637560, -3.364460, -4.359913 ] },
        { "element": "Ag", "location": [ 2.251820, -3.364460, -4.359913 ] },
        { "element": "Ag", "location": [ 5.141200, -3.364460, -4.359913 ] },
        { "element": "Ag", "location": [ 8.030580, -3.364460, -4.359913 ] },
        { "element": "Ag", "location": [ 10.919959, -3.364460, -4.359913 ] },
        { "element": "Ag", "location": [ -9.305699, -0.475080, -4.359913 ] },
        { "element": "Ag", "location": [ -6.416319, -0.475080, -4.359913 ] },
        { "element": "Ag", "location": [ -3.526939, -0.475080, -4.359913 ] },
        { "element": "Ag", "location": [ -0.637560, -0.475080, -4.359913 ] },
        { "element": "Ag", "location": [ 2.251820, -0.475080, -4.359913 ] },
        { "element": "Ag", "location": [ 5.141200, -0.475080, -4.359913 ] },
        { "element": "Ag", "location": [ 8.030580, -0.475080, -4.359913 ] },
        { "element": "Ag", "location": [ 10.919959, -0.475080, -4.359913 ] },
        { "element": "Ag", "location": [ -9.305699, 2.414300, -4.359913 ] },
        { "element": "Ag", "location": [ -6.416319, 2.414300, -4.359913 ] },
        { "element": "Ag", "location": [ -3.526939, 2.414300, -4.359913 ] },
        { "element": "Ag", "location": [ -0.637560, 2.414300, -4.359913 ] },
        { "element": "Ag", "location": [ 2.251820, 2.414300, -4.359913 ] },
        { "element": "Ag", "location": [ 5.141200, 2.414300, -4.359913 ] },
        { "element": "Ag", "location": [ 8.030580, 2.414300, -4.359913 ] },
        { "element": "Ag", "location": [ 10.919959, 2.414300, -4.359913 ] },
        { "element": "Ag", "location": [ -9.305699, 5.303680, -4.359913 ] },
        { "element": "Ag", "location": [ -6.416319, 5.303680, -4.359913 ] },
        { "element": "Ag", "location": [ -3.526939, 5.303680, -4.359913 ] },
        { "element": "Ag", "location": [ -0.637560, 5.303680, -4.359913 ] },
        { "element": "Ag", "location": [ 2.251820, 5.303680, -4.359913 ] },
        { "element": "Ag", "location": [ 5.141200, 5.303680, -4.359913 ] },
        { "element": "Ag", "location": [ 8.030580, 5.303680, -4.359913 ] },
        { "element": "Ag", "location": [ 10.919959, 5.303680, -4.359913 ] },
        { "element": "Ag", "location": [ -9.305699, 8.193059, -4.359913 ] },
        { "element": "Ag", "location": [ -6.416319, 8.193059, -4.359913 ] },
        { "element": "Ag", "location": [ -3.526939, 8.193059, -4.359913 ] },
        { "element": "Ag", "location": [ -0.637560, 8.193059, -4.359913 ] },
        { "element": "Ag", "location": [ 2.251820, 8.193059, -4.359913 ] },
        { "element": "Ag", "location": [ 5.141200, 8.193059, -4.359913 ] },
        { "element": "Ag", "location": [ 8.030580, 8.193059, -4.359913 ] },
        { "element": "Ag", "location": [ 10.919959, 8.193059, -4.359913 ] },
        { "element": "Ag", "location": [ -9.305699, 11.082439, -4.359913 ] },
        { "element": "Ag", "location": [ -6.416319, 11.082439, -4.359913 ] },
        { "element": "Ag", "location": [ -3.526939, 11.082439, -4.359913 ] },
        { "element": "Ag", "location": [ -0.637560, 11.082439, -4.359913 ] },
        { "element": "Ag", "location": [ 2.251820, 11.082439, -4.359913 ] },
        { "element": "Ag", "location": [ 5.141200, 11.082439, -4.359913 ] },
        { "element": "Ag", "location": [ 8.030580, 11.082439, -4.359913 ] },
        { "element": "Ag", "location": [ 10.919959, 11.082439, -4.359913 ] },
        { "element": "Ag", "location": [ -10.761978, -10.651222, -2.221480 ] },
        { "element": "Ag", "location": [ -7.875625, -10.570903, -2.245892 ] },
        { "element": "Ag", "location": [ -4.974425, -10.627110, -2.264842 ] },
        { "element": "Ag", "location": [ -2.072586, -10.560827, -2.225923 ] },
        { "element": "Ag", "location": [ 0.814789, -10.525363, -2.248518 ] },
        { "element": "Ag", "location": [ 3.704729, -10.628790, -2.249498 ] },
        { "element": "Ag", "location": [ 6.594461, -10.579218, -2.241921 ] },
        { "element": "Ag", "location": [ 9.485177, -10.632489, -2.240142 ] },
        { "element": "Ag", "location": [ -10.782222, -7.755407, -2.238767 ] },
        { "element": "Ag", "location": [ -7.890155, -7.664036, -2.273034 ] },
        { "element": "Ag", "location": [ -4.979974, -7.733745, -2.249719 ] },
        { "element": "Ag", "location": [ -2.083491, -7.671795, -2.238367 ] },
        { "element": "Ag", "location": [ 0.795454, -7.640261, -2.238287 ] },
        { "element": "Ag", "location": [ 3.677101, -7.740541, -2.261297 ] },
        { "element": "Ag", "location": [ 6.579628, -7.693964, -2.265882 ] },
        { "element": "Ag", "location": [ 9.470886, -7.742102, -2.235537 ] },
        { "element": "Ag", "location": [ -10.776887, -4.857367, -2.234140 ] },
        { "element": "Ag", "location": [ -7.872007, -4.760355, -2.252863 ] },
        { "element": "Ag", "location": [ -4.977818, -4.831851, -2.269895 ] },
        { "element": "Ag", "location": [ -2.088188, -4.763981, -2.253130 ] },
        { "element": "Ag", "location": [ 0.799139, -4.761897, -2.258912 ] },
        { "element": "Ag", "location": [ 3.688880, -4.858353, -2.258286 ] },
        { "element": "Ag", "location": [ 6.610311, -4.797354, -2.268383 ] },
        { "element": "Ag", "location": [ 9.489041, -4.845194, -2.210983 ] },
        { "element": "Ag", "location": [ -10.745862, -1.976911, -2.232082 ] },
        { "element": "Ag", "location": [ -7.847030, -1.883882, -2.274703 ] },
        { "element": "Ag", "location": [ -4.929769, -1.943851, -2.259368 ] },
        { "element": "Ag", "location": [ -2.051467, -1.881753, -2.245610 ] },
        { "element": "Ag", "location": [ 0.826061, -1.866446, -2.225796 ] },
        { "element": "Ag", "location": [ 3.712827, -1.973959, -2.264529 ] },
        { "element": "Ag", "location": [ 6.610846, -1.897741, -2.245960 ] },
        { "element": "Ag", "location": [ 9.489142, -1.960628, -2.217401 ] },
        { "element": "Ag", "location": [ -10.738722, 0.907605, -2.225842 ] },
        { "element": "Ag", "location": [ -7.851616, 1.014617, -2.282788 ] },
        { "element": "Ag", "location": [ -4.929753, 0.925372, -2.275773 ] },
        { "element": "Ag", "location": [ -2.042083, 0.995359, -2.245729 ] },
        { "element": "Ag", "location": [ 0.857891, 1.007706, -2.278272 ] },
        { "element": "Ag", "location": [ 3.744621, 0.918355, -2.250243 ] },
        { "element": "Ag", "location": [ 6.628368, 0.976181, -2.251064 ] },
        { "element": "Ag", "location": [ 9.507948, 0.909960, -2.211079 ] },
        { "element": "Ag", "location": [ -10.767748, 3.814982, -2.233112 ] },
        { "element": "Ag", "location": [ -7.873946, 3.941225, -2.248473 ] },
        { "element": "Ag", "location": [ -4.961777, 3.839325, -2.264676 ] },
        { "element": "Ag", "location": [ -2.100730, 3.903178, -2.220705 ] },
        { "element": "Ag", "location": [ 0.791987, 3.915729, -2.266889 ] },
        { "element": "Ag", "location": [ 3.689479, 3.820886, -2.258563 ] },
        { "element": "Ag", "location": [ 6.577468, 3.878159, -2.248193 ] },
        { "element": "Ag", "location": [ 9.487316, 3.827976, -2.259719 ] },
        { "element": "Ag", "location": [ -10.802915, 6.702411, -2.227696 ] },
        { "element": "Ag", "location": [ -7.908478, 6.798780, -2.235663 ] },
        { "element": "Ag", "location": [ -5.039701, 6.722435, -2.267932 ] },
        { "element": "Ag", "location": [ -2.132325, 6.777865, -2.241465 ] },
        { "element": "Ag", "location": [ 0.767209, 6.820428, -2.261458 ] },
        { "element": "Ag", "location": [ 3.650441, 6.712875, -2.246302 ] },
        { "element": "Ag", "location": [ 6.567028, 6.780012, -2.254384 ] },
        { "element": "Ag", "location": [ 9.457245, 6.724642, -2.204778 ] },
        { "element": "Ag", "location": [ -10.763073, 9.585285, -2.227107 ] },
        { "element": "Ag", "location": [ -7.864493, 9.668292, -2.223658 ] },
        { "element": "Ag", "location": [ -4.981383, 9.595808, -2.227430 ] },
        { "element": "Ag", "location": [ -2.075053, 9.670201, -2.249377 ] },
        { "element": "Ag", "location": [ 0.809482, 9.705671, -2.211390 ] },
        { "element": "Ag", "location": [ 3.689314, 9.603477, -2.232620 ] },
        { "element": "Ag", "location": [ 6.600264, 9.650481, -2.246007 ] },
        { "element": "Ag", "location": [ 9.491352, 9.590686, -2.215265 ] },
        { "element": "Ag", "location": [ -9.345013, -9.027572, 0.109743 ] },
        { "element": "Ag", "location": [ -6.465144, -9.088604, 0.094104 ] },
        { "element": "Ag", "location": [ -3.588923, -9.273642, 0.109017 ] },
        { "element": "Ag", "location": [ -0.672926, -8.933903, 0.125752 ] },
        { "element": "Ag", "location": [ 2.243832, -9.226639, 0.104235 ] },
        { "element": "Ag", "location": [ 5.140238, -9.193701, 0.100334 ] },
        { "element": "Ag", "location": [ 8.017925, -8.963925, 0.105940 ] },
        { "element": "Ag", "location": [ 10.886443, -9.488792, 0.157748 ] },
        { "element": "Ag", "location": [ -9.314556, -6.150097, 0.095938 ] },
        { "element": "Ag", "location": [ -6.440639, -6.206658, 0.091637 ] },
        { "element": "Ag", "location": [ -3.543366, -6.377774, 0.087298 ] },
        { "element": "Ag", "location": [ -0.658967, -5.994231, 0.120102 ] },
        { "element": "Ag", "location": [ 2.259833, -6.330337, 0.128480 ] },
        { "element": "Ag", "location": [ 5.182615, -6.333942, 0.064053 ] },
        { "element": "Ag", "location": [ 8.042342, -6.080670, 0.106433 ] },
        { "element": "Ag", "location": [ 10.909053, -6.601379, 0.160442 ] },
        { "element": "Ag", "location": [ -9.288341, -3.241577, 0.117529 ] },
        { "element": "Ag", "location": [ -6.433483, -3.311346, 0.085725 ] },
        { "element": "Ag", "location": [ -3.538530, -3.483955, 0.092590 ] },
        { "element": "Ag", "location": [ -0.630114, -3.167285, 0.143828 ] },
        { "element": "Ag", "location": [ 2.246346, -3.468367, 0.078835 ] },
        { "element": "Ag", "location": [ 5.185071, -3.421333, 0.055346 ] },
        { "element": "Ag", "location": [ 8.033596, -3.177317, 0.148097 ] },
        { "element": "Ag", "location": [ 10.927501, -3.693290, 0.178519 ] },
        { "element": "Ag", "location": [ -9.247205, -0.372405, 0.111499 ] },
        { "element": "Ag", "location": [ -6.400980, -0.448056, 0.075050 ] },
        { "element": "Ag", "location": [ -3.460785, -0.583650, 0.127329 ] },
        { "element": "Ag", "location": [ -0.558955, -0.273717, 0.113186 ] },
        { "element": "Ag", "location": [ 2.360442, -0.541483, 0.103953 ] },
        { "element": "Ag", "location": [ 5.220994, -0.521592, 0.126481 ] },
        { "element": "Ag", "location": [ 8.076128, -0.311586, 0.167161 ] },
        { "element": "Ag", "location": [ 10.963571, -0.813727, 0.167288 ] },
        { "element": "Ag", "location": [ -9.293725, 2.525759, 0.098478 ] },
        { "element": "Ag", "location": [ -6.425990, 2.474537, 0.000395 ] },
        { "element": "Ag", "location": [ -3.483073, 2.274793, 0.075012 ] },
        { "element": "Ag", "location": [ -0.531947, 2.573522, 0.064786 ] },
        { "element": "Ag", "location": [ 2.310481, 2.327362, 0.106772 ] },
        { "element": "Ag", "location": [ 5.180405, 2.363731, 0.112286 ] },
        { "element": "Ag", "location": [ 8.079129, 2.605118, 0.095950 ] },
        { "element": "Ag", "location": [ 10.943542, 2.081427, 0.163715 ] },
        { "element": "Ag", "location": [ -9.344737, 5.413101, 0.132225 ] },
        { "element": "Ag", "location": [ -6.474559, 5.404315, 0.154658 ] },
        { "element": "Ag", "location": [ -3.685594, 5.257853, 0.117932 ] },
        { "element": "Ag", "location": [ -0.669703, 5.531855, 0.085213 ] },
        { "element": "Ag", "location": [ 2.214436, 5.223855, 0.092127 ] },
        { "element": "Ag", "location": [ 5.104164, 5.267923, 0.104094 ] },
        { "element": "Ag", "location": [ 8.000176, 5.466654, 0.103943 ] },
        { "element": "Ag", "location": [ 10.897504, 4.972500, 0.159986 ] },
        { "element": "Ag", "location": [ -9.355340, 8.301018, 0.127089 ] },
        { "element": "Ag", "location": [ -6.473634, 8.218142, 0.177332 ] },
        { "element": "Ag", "location": [ -3.626760, 8.086564, 0.108595 ] },
        { "element": "Ag", "location": [ -0.688334, 8.413494, 0.122256 ] },
        { "element": "Ag", "location": [ 2.218554, 8.103951, 0.128834 ] },
        { "element": "Ag", "location": [ 5.122223, 8.156279, 0.106784 ] },
        { "element": "Ag", "location": [ 8.008964, 8.374069, 0.139191 ] },
        { "element": "Ag", "location": [ 10.900396, 7.878734, 0.178812 ] },
        { "element": "Ag", "location": [ -9.285877, 11.187236, 0.142863 ] },
        { "element": "Ag", "location": [ -6.386500, 11.134327, 0.120586 ] },
        { "element": "Ag", "location": [ -3.484658, 10.964153, 0.107619 ] },
        { "element": "Ag", "location": [ -0.569098, 11.326275, 0.155356 ] },
        { "element": "Ag", "location": [ 2.309310, 11.015117, 0.136628 ] },
        { "element": "Ag", "location": [ 5.196861, 11.045050, 0.114522 ] },
        { "element": "Ag", "location": [ 8.080148, 11.272167, 0.126838 ] },
        { "element": "Ag", "location": [ 10.946203, 10.748893, 0.162226 ] },
        { "element": "Ag", "location": [ -10.669935, -10.978006, 2.240438 ] },
        { "element": "Ag", "location": [ -7.862814, -9.924286, 2.260677 ] },
        { "element": "Ag", "location": [ -5.009823, -11.066551, 2.212718 ] },
        { "element": "Ag", "location": [ -2.085275, -10.412426, 2.185359 ] },
        { "element": "Ag", "location": [ 0.968965, -10.194701, 2.397564 ] },
        { "element": "Ag", "location": [ 3.782226, -11.168589, 2.282263 ] },
        { "element": "Ag", "location": [ 6.583876, -9.956128, 2.284130 ] },
        { "element": "Ag", "location": [ 9.394162, -10.984066, 2.248457 ] },
        { "element": "Ag", "location": [ -10.713716, -8.084565, 2.218097 ] },
        { "element": "Ag", "location": [ -7.920089, -7.000947, 2.239669 ] },
        { "element": "Ag", "location": [ -5.146956, -8.193337, 2.260761 ] },
        { "element": "Ag", "location": [ -2.377595, -7.530098, 2.157458 ] },
        { "element": "Ag", "location": [ 0.723625, -7.381098, 2.093566 ] },
        { "element": "Ag", "location": [ 3.742004, -8.270417, 2.340903 ] },
        { "element": "Ag", "location": [ 6.556947, -7.070144, 2.274745 ] },
        { "element": "Ag", "location": [ 9.354353, -8.098658, 2.248078 ] },
        { "element": "Ag", "location": [ -10.696807, -5.178756, 2.219717 ] },
        { "element": "Ag", "location": [ -7.880002, -4.086297, 2.233230 ] },
        { "element": "Ag", "location": [ -5.078275, -5.303510, 2.210408 ] },
        { "element": "Ag", "location": [ -2.205267, -4.689874, 2.293493 ] },
        { "element": "Ag", "location": [ 0.864394, -4.357314, 2.394609 ] },
        { "element": "Ag", "location": [ 3.813068, -5.358269, 2.196005 ] },
        { "element": "Ag", "location": [ 6.638934, -4.169018, 2.278118 ] },
        { "element": "Ag", "location": [ 9.387066, -5.227077, 2.249790 ] },
        { "element": "Ag", "location": [ -10.592331, -2.283050, 2.239974 ] },
        { "element": "Ag", "location": [ -7.784116, -1.184975, 2.426865 ] },
        { "element": "Ag", "location": [ -5.038592, -2.361087, 2.302956 ] },
        { "element": "Ag", "location": [ -2.101356, -1.816120, 2.207413 ] },
        { "element": "Ag", "location": [ 0.964091, -1.567220, 2.251722 ] },
        { "element": "Ag", "location": [ 3.855941, -2.491000, 2.142287 ] },
        { "element": "Ag", "location": [ 6.602027, -1.306492, 2.508749 ] },
        { "element": "Ag", "location": [ 9.425008, -2.308295, 2.263290 ] },
        { "element": "Ag", "location": [ -10.670430, 0.590236, 2.224693 ] },
        { "element": "Ag", "location": [ -7.930299, 1.693514, 2.209691 ] },
        { "element": "Ag", "location": [ -5.030301, 0.673814, 2.089937 ] },
        { "element": "Ag", "location": [ -1.774223, 1.082433, 2.367945 ] },
        { "element": "Ag", "location": [ 1.106452, 1.383145, 2.239606 ] },
        { "element": "Ag", "location": [ 3.870299, 0.451632, 2.444787 ] },
        { "element": "Ag", "location": [ 6.608036, 1.616103, 2.247210 ] },
        { "element": "Ag", "location": [ 9.388109, 0.554349, 2.239828 ] },
        { "element": "Ag", "location": [ -10.770725, 3.493705, 2.273897 ] },
        { "element": "Ag", "location": [ -8.052781, 4.581108, 2.258967 ] },
        { "element": "Ag", "location": [ -5.183485, 3.496397, 2.114329 ] },
        { "element": "Ag", "location": [ -2.087408, 3.951333, 1.903345 ] },
        { "element": "Ag", "location": [ 0.879173, 4.249359, 2.311335 ] },
        { "element": "Ag", "location": [ 3.725714, 3.319356, 2.269511 ] },
        { "element": "Ag", "location": [ 6.491255, 4.505449, 2.229210 ] },
        { "element": "Ag", "location": [ 9.333605, 3.486039, 2.210802 ] },
        { "element": "Ag", "location": [ -10.800420, 6.380274, 2.291701 ] },
        { "element": "Ag", "location": [ -7.984333, 7.434492, 2.343674 ] },
        { "element": "Ag", "location": [ -5.247949, 6.380394, 2.696066 ] },
        { "element": "Ag", "location": [ -2.274584, 6.937724, 2.200869 ] },
        { "element": "Ag", "location": [ 0.735572, 7.122910, 2.284180 ] },
        { "element": "Ag", "location": [ 3.613614, 6.212552, 2.249870 ] },
        { "element": "Ag", "location": [ 6.469201, 7.383278, 2.242754 ] },
        { "element": "Ag", "location": [ 9.308636, 6.372511, 2.227425 ] },
        { "element": "Ag", "location": [ -10.698628, 9.263750, 2.286073 ] },
        { "element": "Ag", "location": [ -7.865890, 10.314126, 2.269957 ] },
        { "element": "Ag", "location": [ -5.034246, 9.112608, 2.232226 ] },
        { "element": "Ag", "location": [ -2.135091, 9.819633, 2.177571 ] },
        { "element": "Ag", "location": [ 0.912580, 10.022736, 2.218654 ] },
        { "element": "Ag", "location": [ 3.728102, 9.090238, 2.269191 ] },
        { "element": "Ag", "location": [ 6.566137, 10.264422, 2.276672 ] },
        { "element": "Ag", "location": [ 9.401279, 9.249385, 2.253543 ] },
        { "element": "C", "location": [ -5.727904, -1.675115, 4.979711 ] },
        { "element": "C", "location": [ -4.339522, -1.597505, 4.796762 ] },
        { "element": "C", "location": [ -6.577257, -0.558733, 4.984484 ] },
        { "element": "C", "location": [ -4.342462, 4.720669, 4.366518 ] },
        { "element": "C", "location": [ -4.562390, 0.889445, 4.630105 ] },
        { "element": "C", "location": [ -5.971359, 0.707378, 4.820266 ] },
        { "element": "C", "location": [ -3.714944, -0.323956, 4.651924 ] },
        { "element": "C", "location": [ -3.919004, 2.296312, 4.556444 ] },
        { "element": "C", "location": [ -2.521134, 2.347359, 4.279552 ] },
        { "element": "C", "location": [ -2.012412, 3.674084, 4.445223 ] },
        { "element": "C", "location": [ -0.587497, 3.898577, 4.623476 ] },
        { "element": "C", "location": [ -0.048136, 5.171126, 4.814283 ] },
        { "element": "C", "location": [ -0.902581, 6.301166, 4.817584 ] },
        { "element": "C", "location": [ -2.290326, 6.169025, 4.663731 ] },
        { "element": "C", "location": [ -2.934018, 4.871038, 4.490897 ] },
        { "element": "C", "location": [ -2.302315, -0.333595, 4.397985 ] },
        { "element": "C", "location": [ -1.156014, -0.720338, 4.826012 ] },
        { "element": "C", "location": [ -4.742991, 3.404628, 4.605677 ] },
        { "element": "C", "location": [ 2.589927, -1.562632, 4.868578 ] },
        { "element": "C", "location": [ 3.461492, -2.735291, 4.818378 ] },
        { "element": "C", "location": [ 4.880374, -2.570879, 4.931675 ] },
        { "element": "C", "location": [ 5.468696, -1.306752, 5.006294 ] },
        { "element": "C", "location": [ 4.630036, -0.155252, 5.011891 ] },
        { "element": "C", "location": [ 3.236664, -0.284376, 4.930290 ] },
        { "element": "C", "location": [ 2.945429, -4.054004, 4.842346 ] },
        { "element": "C", "location": [ 2.700090, -5.249123, 4.511639 ] },
        { "element": "C", "location": [ 2.289582, -6.602717, 4.728829 ] },
        { "element": "C", "location": [ 3.246408, -7.650312, 4.850931 ] },
        { "element": "C", "location": [ 2.839312, -8.986402, 4.972875 ] },
        { "element": "C", "location": [ 1.455202, -9.327329, 4.964683 ] },
        { "element": "C", "location": [ 0.494317, -8.323458, 4.866053 ] },
        { "element": "C", "location": [ 0.877207, -6.952100, 4.677667 ] },
        { "element": "C", "location": [ -0.056245, -5.897140, 4.676917 ] },
        { "element": "C", "location": [ -0.731275, -4.859561, 4.362090 ] },
        { "element": "C", "location": [ 1.161572, -1.707485, 4.813298 ] },
        { "element": "C", "location": [ 0.220671, -0.632666, 4.835014 ] },
        { "element": "H", "location": [ -6.129824, -2.677919, 5.181490 ] },
        { "element": "H", "location": [ -6.582817, 1.620076, 4.859864 ] },
        { "element": "H", "location": [ 0.046560, 2.998171, 4.714643 ] },
        { "element": "H", "location": [ 1.017674, 5.298387, 5.054428 ] },
        { "element": "H", "location": [ -0.462195, 7.284291, 5.042426 ] },
        { "element": "H", "location": [ -2.935245, 7.042860, 4.867573 ] },
        { "element": "H", "location": [ -3.723429, -2.506555, 4.877374 ] },
        { "element": "H", "location": [ -7.646361, -0.687139, 5.208562 ] },
        { "element": "H", "location": [ 0.617495, 0.399456, 4.920437 ] },
        { "element": "H", "location": [ -5.809262, 3.138212, 4.850097 ] },
        { "element": "H", "location": [ 1.152434, -10.353669, 5.219101 ] },
        { "element": "H", "location": [ 4.304978, -7.389225, 4.997633 ] },
        { "element": "H", "location": [ 5.513566, -3.469610, 4.980847 ] },
        { "element": "H", "location": [ 6.533972, -1.207263, 5.262783 ] },
        { "element": "H", "location": [ 5.075744, 0.834607, 5.185717 ] },
        { "element": "H", "location": [ 2.618139, 0.612561, 5.083693 ] },
        { "element": "H", "location": [ -0.574411, -8.573190, 4.923496 ] },
        { "element": "H", "location": [ 3.587333, -9.771455, 5.149647 ] },
        { "element": "H", "location": [ -1.149964, -4.095583, 5.029784 ] },
        { "element": "H", "location": [ 0.777798, -2.736649, 4.913771 ] }
    ],
    "bonds": [
        { "atoms": [ 0, 1 ], "order": 1 },
        { "atoms": [ 0, 8 ], "order": 1 },
        { "atoms": [ 0, 65 ], "order": 1 },
        { "atoms": [ 0, 72 ], "order": 1 },
        { "atoms": [ 0, 64 ], "order": 1 },
        { "atoms": [ 1, 2 ], "order": 1 },
        { "atoms": [ 1, 9 ], "order": 1 },
        { "atoms": [ 1, 66 ], "order": 1 },
        { "atoms": [ 1, 74 ], "order": 1 },
        { "atoms": [ 1, 65 ], "order": 1 },
        { "atoms": [ 2, 3 ], "order": 1 },
        { "atoms": [ 2, 10 ], "order": 1 },
        { "atoms": [ 2, 66 ], "order": 1 },
        { "atoms": [ 2, 74 ], "order": 1 },
        { "atoms": [ 2, 67 ], "order": 1 },
        { "atoms": [ 3, 4 ], "order": 1 },
        { "atoms": [ 3, 11 ], "order": 1 },
        { "atoms": [ 3, 68 ], "order": 1 },
        { "atoms": [ 3, 67 ], "order": 1 },
        { "atoms": [ 4, 5 ], "order": 1 },
        { "atoms": [ 4, 12 ], "order": 1 },
        { "atoms": [ 4, 77 ], "order": 1 },
        { "atoms": [ 4, 69 ], "order": 1 },
        { "atoms": [ 4, 68 ], "order": 1 },
        { "atoms": [ 5, 6 ], "order": 1 },
        { "atoms": [ 5, 13 ], "order": 1 },
        { "atoms": [ 5, 78 ], "order": 1 },
        { "atoms": [ 5, 77 ], "order": 1 },
        { "atoms": [ 5, 70 ], "order": 1 },
        { "atoms": [ 6, 7 ], "order": 1 },
        { "atoms": [ 6, 14 ], "order": 1 },
        { "atoms": [ 6, 70 ], "order": 1 },
        { "atoms": [ 6, 79 ], "order": 1 },
        { "atoms": [ 7, 15 ], "order": 1 },
        { "atoms": [ 7, 71 ], "order": 1 },
        { "atoms": [ 7, 79 ], "order": 1 },
        { "atoms": [ 8, 9 ], "order": 1 },
        { "atoms": [ 8, 16 ], "order": 1 },
        { "atoms": [ 8, 73 ], "order": 1 },
        { "atoms": [ 8, 80 ], "order": 1 },
        { "atoms": [ 9, 10 ], "order": 1 },
        { "atoms": [ 9, 17 ], "order": 1 },
        { "atoms": [ 9, 73 ], "order": 1 },
        { "atoms": [ 9, 82 ], "order": 1 },
        { "atoms": [ 10, 11 ], "order": 1 },
        { "atoms": [ 10, 18 ], "order": 1 },
        { "atoms": [ 10, 82 ], "order": 1 },
        { "atoms": [ 10, 75 ], "order": 1 },
        { "atoms": [ 11, 12 ], "order": 1 },
        { "atoms": [ 11, 19 ], "order": 1 },
        { "atoms": [ 11, 75 ], "order": 1 },
        { "atoms": [ 11, 76 ], "order": 1 },
        { "atoms": [ 12, 13 ], "order": 1 },
        { "atoms": [ 12, 20 ], "order": 1 },
        { "atoms": [ 12, 85 ], "order": 1 },
        { "atoms": [ 12, 76 ], "order": 1 },
        { "atoms": [ 13, 14 ], "order": 1 },
        { "atoms": [ 13, 21 ], "order": 1 },
        { "atoms": [ 13, 78 ], "order": 1 },
        { "atoms": [ 13, 85 ], "order": 1 },
        { "atoms": [ 14, 15 ], "order": 1 },
        { "atoms": [ 14, 22 ], "order": 1 },
        { "atoms": [ 14, 86 ], "order": 1 },
        { "atoms": [ 15, 23 ], "order": 1 },
        { "atoms": [ 15, 79 ], "order": 1 },
        { "atoms": [ 15, 87 ], "order": 1 },
        { "atoms": [ 16, 17 ], "order": 1 },
        { "atoms": [ 16, 24 ], "order": 1 },
        { "atoms": [ 16, 81 ], "order": 1 },
        { "atoms": [ 16, 88 ], "order": 1 },
        { "atoms": [ 17, 18 ], "order": 1 },
        { "atoms": [ 17, 25 ], "order": 1 },
        { "atoms": [ 17, 81 ], "order": 1 },
        { "atoms": [ 18, 19 ], "order": 1 },
        { "atoms": [ 18, 26 ], "order": 1 },
        { "atoms": [ 18, 90 ], "order": 1 },
        { "atoms": [ 18, 83 ], "order": 1 },
        { "atoms": [ 19, 20 ], "order": 1 },
        { "atoms": [ 19, 27 ], "order": 1 },
        { "atoms": [ 19, 84 ], "order": 1 },
        { "atoms": [ 19, 83 ], "order": 1 },
        { "atoms": [ 20, 21 ], "order": 1 },
        { "atoms": [ 20, 28 ], "order": 1 },
        { "atoms": [ 20, 93 ], "order": 1 },
        { "atoms": [ 20, 84 ], "order": 1 },
        { "atoms": [ 21, 22 ], "order": 1 },
        { "atoms": [ 21, 29 ], "order": 1 },
        { "atoms": [ 21, 93 ], "order": 1 },
        { "atoms": [ 22, 23 ], "order": 1 },
        { "atoms": [ 22, 30 ], "order": 1 },
        { "atoms": [ 22, 86 ], "order": 1 },
        { "atoms": [ 22, 94 ], "order": 1 },
        { "atoms": [ 23, 31 ], "order": 1 },
        { "atoms": [ 23, 95 ], "order": 1 },
        { "atoms": [ 23, 87 ], "order": 1 },
        { "atoms": [ 24, 25 ], "order": 1 },
        { "atoms": [ 24, 32 ], "order": 1 },
        { "atoms": [ 24, 89 ], "order": 1 },
        { "atoms": [ 24, 96 ], "order": 1 },
        { "atoms": [ 25, 26 ], "order": 1 },
        { "atoms": [ 25, 33 ], "order": 1 },
        { "atoms": [ 25, 98 ], "order": 1 },
        { "atoms": [ 25, 89 ], "order": 1 },
        { "atoms": [ 26, 27 ], "order": 1 },
        { "atoms": [ 26, 34 ], "order": 1 },
        { "atoms": [ 26, 98 ], "order": 1 },
        { "atoms": [ 26, 90 ], "order": 1 },
        { "atoms": [ 27, 28 ], "order": 1 },
        { "atoms": [ 27, 35 ], "order": 1 },
        { "atoms": [ 27, 99 ], "order": 1 },
        { "atoms": [ 27, 91 ], "order": 1 },
        { "atoms": [ 28, 29 ], "order": 1 },
        { "atoms": [ 28, 36 ], "order": 1 },
        { "atoms": [ 28, 100 ], "order": 1 },
        { "atoms": [ 28, 92 ], "order": 1 },
        { "atoms": [ 29, 30 ], "order": 1 },
        { "atoms": [ 29, 37 ], "order": 1 },
        { "atoms": [ 29, 101 ], "order": 1 },
        { "atoms": [ 30, 31 ], "order": 1 },
        { "atoms": [ 30, 38 ], "order": 1 },
        { "atoms": [ 30, 102 ], "order": 1 },
        { "atoms": [ 30, 94 ], "order": 1 },
        { "atoms": [ 31, 39 ], "order": 1 },
        { "atoms": [ 31, 95 ], "order": 1 },
        { "atoms": [ 31, 103 ], "order": 1 },
        { "atoms": [ 32, 33 ], "order": 1 },
        { "atoms": [ 32, 40 ], "order": 1 },
        { "atoms": [ 32, 97 ], "order": 1 },
        { "atoms": [ 32, 104 ], "order": 1 },
        { "atoms": [ 33, 34 ], "order": 1 },
        { "atoms": [ 33, 41 ], "order": 1 },
        { "atoms": [ 33, 97 ], "order": 1 },
        { "atoms": [ 33, 106 ], "order": 1 },
        { "atoms": [ 34, 35 ], "order": 1 },
        { "atoms": [ 34, 42 ], "order": 1 },
        { "atoms": [ 34, 98 ], "order": 1 },
        { "atoms": [ 34, 106 ], "order": 1 },
        { "atoms": [ 35, 36 ], "order": 1 },
        { "atoms": [ 35, 43 ], "order": 1 },
        { "atoms": [ 35, 99 ], "order": 1 },
        { "atoms": [ 36, 37 ], "order": 1 },
        { "atoms": [ 36, 44 ], "order": 1 },
        { "atoms": [ 36, 100 ], "order": 1 },
        { "atoms": [ 36, 109 ], "order": 1 },
        { "atoms": [ 37, 38 ], "order": 1 },
        { "atoms": [ 37, 45 ], "order": 1 },
        { "atoms": [ 37, 109 ], "order": 1 },
        { "atoms": [ 37, 101 ], "order": 1 },
        { "atoms": [ 38, 39 ], "order": 1 },
        { "atoms": [ 38, 46 ], "order": 1 },
        { "atoms": [ 38, 111 ], "order": 1 },
        { "atoms": [ 38, 102 ], "order": 1 },
        { "atoms": [ 39, 47 ], "order": 1 },
        { "atoms": [ 39, 111 ], "order": 1 },
        { "atoms": [ 39, 103 ], "order": 1 },
        { "atoms": [ 40, 41 ], "order": 1 },
        { "atoms": [ 40, 48 ], "order": 1 },
        { "atoms": [ 40, 105 ], "order": 1 },
        { "atoms": [ 40, 113 ], "order": 1 },
        { "atoms": [ 40, 112 ], "order": 1 },
        { "atoms": [ 41, 42 ], "order": 1 },
        { "atoms": [ 41, 49 ], "order": 1 },
        { "atoms": [ 41, 114 ], "order": 1 },
        { "atoms": [ 41, 105 ], "order": 1 },
        { "atoms": [ 42, 43 ], "order": 1 },
        { "atoms": [ 42, 50 ], "order": 1 },
        { "atoms": [ 42, 107 ], "order": 1 },
        { "atoms": [ 43, 44 ], "order": 1 },
        { "atoms": [ 43, 51 ], "order": 1 },
        { "atoms": [ 43, 108 ], "order": 1 },
        { "atoms": [ 44, 45 ], "order": 1 },
        { "atoms": [ 44, 52 ], "order": 1 },
        { "atoms": [ 44, 108 ], "order": 1 },
        { "atoms": [ 44, 117 ], "order": 1 },
        { "atoms": [ 45, 46 ], "order": 1 },
        { "atoms": [ 45, 53 ], "order": 1 },
        { "atoms": [ 45, 110 ], "order": 1 },
        { "atoms": [ 46, 47 ], "order": 1 },
        { "atoms": [ 46, 54 ], "order": 1 },
        { "atoms": [ 46, 110 ], "order": 1 },
        { "atoms": [ 46, 119 ], "order": 1 },
        { "atoms": [ 47, 55 ], "order": 1 },
        { "atoms": [ 47, 111 ], "order": 1 },
        { "atoms": [ 47, 119 ], "order": 1 },
        { "atoms": [ 48, 49 ], "order": 1 },
        { "atoms": [ 48, 56 ], "order": 1 },
        { "atoms": [ 48, 113 ], "order": 1 },
        { "atoms": [ 48, 120 ], "order": 1 },
        { "atoms": [ 48, 121 ], "order": 1 },
        { "atoms": [ 49, 50 ], "order": 1 },
        { "atoms": [ 49, 57 ], "order": 1 },
        { "atoms": [ 49, 114 ], "order": 1 },
        { "atoms": [ 49, 122 ], "order": 1 },
        { "atoms": [ 50, 51 ], "order": 1 },
        { "atoms": [ 50, 58 ], "order": 1 },
        { "atoms": [ 50, 115 ], "order": 1 },
        { "atoms": [ 50, 122 ], "order": 1 },
        { "atoms": [ 51, 52 ], "order": 1 },
        { "atoms": [ 51, 59 ], "order": 1 },
        { "atoms": [ 51, 116 ], "order": 1 },
        { "atoms": [ 51, 123 ], "order": 1 },
        { "atoms": [ 52, 53 ], "order": 1 },
        { "atoms": [ 52, 60 ], "order": 1 },
        { "atoms": [ 52, 116 ], "order": 1 },
        { "atoms": [ 52, 125 ], "order": 1 },
        { "atoms": [ 53, 54 ], "order": 1 },
        { "atoms": [ 53, 61 ], "order": 1 },
        { "atoms": [ 53, 118 ], "order": 1 },
        { "atoms": [ 53, 125 ], "order": 1 },
        { "atoms": [ 54, 55 ], "order": 1 },
        { "atoms": [ 54, 62 ], "order": 1 },
        { "atoms": [ 54, 118 ], "order": 1 },
        { "atoms": [ 54, 126 ], "order": 1 },
        { "atoms": [ 55, 63 ], "order": 1 },
        { "atoms": [ 55, 127 ], "order": 1 },
        { "atoms": [ 55, 119 ], "order": 1 },
        { "atoms": [ 56, 57 ], "order": 1 },
        { "atoms": [ 56, 120 ], "order": 1 },
        { "atoms": [ 56, 121 ], "order": 1 },
        { "atoms": [ 57, 58 ], "order": 1 },
        { "atoms": [ 57, 122 ], "order": 1 },
        { "atoms": [ 57, 121 ], "order": 1 },
        { "atoms": [ 58, 59 ], "order": 1 },
        { "atoms": [ 58, 123 ], "order": 1 },
        { "atoms": [ 59, 60 ], "order": 1 },
        { "atoms": [ 59, 123 ], "order": 1 },
        { "atoms": [ 59, 124 ], "order": 1 },
        { "atoms": [ 60, 61 ], "order": 1 },
        { "atoms": [ 60, 125 ], "order": 1 },
        { "atoms": [ 60, 124 ], "order": 1 },
        { "atoms": [ 61, 62 ], "order": 1 },
        { "atoms": [ 61, 126 ], "order": 1 },
        { "atoms": [ 62, 63 ], "order": 1 },
        { "atoms": [ 62, 126 ], "order": 1 },
        { "atoms": [ 62, 127 ], "order": 1 },
        { "atoms": [ 63, 127 ], "order": 1 },
        { "atoms": [ 97, 89 ], "order": 1 },
        { "atoms": [ 97, 105 ], "order": 1 },
        { "atoms": [ 97, 96 ], "order": 1 },
        { "atoms": [ 100, 108 ], "order": 1 },
        { "atoms": [ 100, 101 ], "order": 1 },
        { "atoms": [ 100, 99 ], "order": 1 },
        { "atoms": [ 100, 92 ], "order": 1 },
        { "atoms": [ 98, 106 ], "order": 1 },
        { "atoms": [ 98, 90 ], "order": 1 },
        { "atoms": [ 98, 99 ], "order": 1 },
        { "atoms": [ 89, 90 ], "order": 1 },
        { "atoms": [ 89, 81 ], "order": 1 },
        { "atoms": [ 89, 88 ], "order": 1 },
        { "atoms": [ 73, 81 ], "order": 1 },
        { "atoms": [ 73, 74 ], "order": 1 },
        { "atoms": [ 73, 65 ], "order": 1 },
        { "atoms": [ 73, 72 ], "order": 1 },
        { "atoms": [ 82, 90 ], "order": 1 },
        { "atoms": [ 82, 83 ], "order": 1 },
        { "atoms": [ 82, 81 ], "order": 1 },
        { "atoms": [ 82, 74 ], "order": 1 },
        { "atoms": [ 86, 78 ], "order": 1 },
        { "atoms": [ 86, 85 ], "order": 1 },
        { "atoms": [ 86, 94 ], "order": 1 },
        { "atoms": [ 86, 87 ], "order": 1 },
        { "atoms": [ 114, 106 ], "order": 1 },
        { "atoms": [ 114, 115 ], "order": 1 },
        { "atoms": [ 114, 113 ], "order": 1 },
        { "atoms": [ 114, 122 ], "order": 1 },
        { "atoms": [ 108, 116 ], "order": 1 },
        { "atoms": [ 108, 109 ], "order": 1 },
        { "atoms": [ 108, 107 ], "order": 1 },
        { "atoms": [ 78, 77 ], "order": 1 },
        { "atoms": [ 78, 70 ], "order": 1 },
        { "atoms": [ 78, 79 ], "order": 1 },
        { "atoms": [ 66, 74 ], "order": 1 },
        { "atoms": [ 66, 65 ], "order": 1 },
        { "atoms": [ 66, 67 ], "order": 1 },
        { "atoms": [ 106, 105 ], "order": 1 },
        { "atoms": [ 106, 107 ], "order": 1 },
        { "atoms": [ 93, 85 ], "order": 1 },
        { "atoms": [ 93, 101 ], "order": 1 },
        { "atoms": [ 93, 94 ], "order": 1 },
        { "atoms": [ 93, 92 ], "order": 1 },
        { "atoms": [ 116, 117 ], "order": 1 },
        { "atoms": [ 116, 115 ], "order": 1 },
        { "atoms": [ 116, 124 ], "order": 1 },
        { "atoms": [ 77, 85 ], "order": 1 },
        { "atoms": [ 77, 69 ], "order": 1 },
        { "atoms": [ 77, 76 ], "order": 1 },
        { "atoms": [ 111, 110 ], "order": 1 },
        { "atoms": [ 111, 103 ], "order": 1 },
        { "atoms": [ 111, 119 ], "order": 1 },
        { "atoms": [ 90, 91 ], "order": 1 },
        { "atoms": [ 84, 85 ], "order": 1 },
        { "atoms": [ 84, 83 ], "order": 1 },
        { "atoms": [ 84, 76 ], "order": 1 },
        { "atoms": [ 84, 92 ], "order": 1 },
        { "atoms": [ 109, 101 ], "order": 1 },
        { "atoms": [ 109, 110 ], "order": 1 },
        { "atoms": [ 109, 117 ], "order": 1 },
        { "atoms": [ 118, 110 ], "order": 1 },
        { "atoms": [ 118, 117 ], "order": 1 },
        { "atoms": [ 118, 126 ], "order": 1 },
        { "atoms": [ 118, 119 ], "order": 1 },
        { "atoms": [ 83, 91 ], "order": 1 },
        { "atoms": [ 83, 75 ], "order": 1 },
        { "atoms": [ 81, 80 ], "order": 1 },
        { "atoms": [ 102, 101 ], "order": 1 },
        { "atoms": [ 102, 110 ], "order": 1 },
        { "atoms": [ 102, 94 ], "order": 1 },
        { "atoms": [ 102, 103 ], "order": 1 },
        { "atoms": [ 74, 75 ], "order": 1 },
        { "atoms": [ 69, 68 ], "order": 1 },
        { "atoms": [ 69, 70 ], "order": 1 },
        { "atoms": [ 123, 115 ], "order": 1 },
        { "atoms": [ 123, 122 ], "order": 1 },
        { "atoms": [ 123, 124 ], "order": 1 },
        { "atoms": [ 68, 76 ], "order": 1 },
        { "atoms": [ 68, 67 ], "order": 1 },
        { "atoms": [ 68, 132 ], "order": 1 },
        { "atoms": [ 105, 113 ], "order": 1 },
        { "atoms": [ 105, 104 ], "order": 1 },
        { "atoms": [ 117, 125 ], "order": 1 },
        { "atoms": [ 126, 125 ], "order": 1 },
        { "atoms": [ 126, 127 ], "order": 1 },
        { "atoms": [ 94, 95 ], "order": 1 },
        { "atoms": [ 65, 64 ], "order": 1 },
        { "atoms": [ 65, 129 ], "order": 1 },
        { "atoms": [ 99, 91 ], "order": 1 },
        { "atoms": [ 99, 107 ], "order": 1 },
        { "atoms": [ 91, 92 ], "order": 1 },
        { "atoms": [ 70, 71 ], "order": 1 },
        { "atoms": [ 70, 133 ], "order": 1 },
        { "atoms": [ 115, 107 ], "order": 1 },
        { "atoms": [ 71, 79 ], "order": 1 },
        { "atoms": [ 71, 135 ], "order": 1 },
        { "atoms": [ 72, 80 ], "order": 1 },
        { "atoms": [ 72, 64 ], "order": 1 },
        { "atoms": [ 72, 128 ], "order": 1 },
        { "atoms": [ 75, 76 ], "order": 1 },
        { "atoms": [ 75, 67 ], "order": 1 },
        { "atoms": [ 113, 112 ], "order": 1 },
        { "atoms": [ 113, 121 ], "order": 1 },
        { "atoms": [ 79, 87 ], "order": 1 },
        { "atoms": [ 80, 88 ], "order": 1 },
        { "atoms": [ 80, 136 ], "order": 1 },
        { "atoms": [ 104, 112 ], "order": 1 },
        { "atoms": [ 104, 96 ], "order": 1 },
        { "atoms": [ 104, 160 ], "order": 1 },
        { "atoms": [ 125, 124 ], "order": 1 },
        { "atoms": [ 88, 96 ], "order": 1 },
        { "atoms": [ 88, 144 ], "order": 1 },
        { "atoms": [ 112, 120 ], "order": 1 },
        { "atoms": [ 112, 168 ], "order": 1 },
        { "atoms": [ 122, 121 ], "order": 1 },
        { "atoms": [ 120, 121 ], "order": 1 },
        { "atoms": [ 120, 176 ], "order": 1 },
        { "atoms": [ 120, 184 ], "order": 1 },
        { "atoms": [ 96, 152 ], "order": 1 },
        { "atoms": [ 64, 128 ], "order": 1 },
        { "atoms": [ 95, 103 ], "order": 1 },
        { "atoms": [ 95, 87 ], "order": 1 },
        { "atoms": [ 95, 159 ], "order": 1 },
        { "atoms": [ 127, 119 ], "order": 1 },
        { "atoms": [ 127, 191 ], "order": 1 },
        { "atoms": [ 103, 167 ], "order": 1 },
        { "atoms": [ 161, 162 ], "order": 1 },
        { "atoms": [ 161, 153 ], "order": 1 },
        { "atoms": [ 161, 160 ], "order": 1 },
        { "atoms": [ 161, 169 ], "order": 1 },
        { "atoms": [ 161, 234 ], "order": 1 },
        { "atoms": [ 161, 225 ], "order": 1 },
        { "atoms": [ 149, 141 ], "order": 1 },
        { "atoms": [ 149, 148 ], "order": 1 },
        { "atoms": [ 149, 157 ], "order": 1 },
        { "atoms": [ 149, 150 ], "order": 1 },
        { "atoms": [ 149, 221 ], "order": 1 },
        { "atoms": [ 149, 214 ], "order": 1 },
        { "atoms": [ 141, 133 ], "order": 1 },
        { "atoms": [ 141, 142 ], "order": 1 },
        { "atoms": [ 141, 140 ], "order": 1 },
        { "atoms": [ 141, 213 ], "order": 1 },
        { "atoms": [ 141, 206 ], "order": 1 },
        { "atoms": [ 163, 162 ], "order": 1 },
        { "atoms": [ 163, 171 ], "order": 1 },
        { "atoms": [ 163, 164 ], "order": 1 },
        { "atoms": [ 163, 155 ], "order": 1 },
        { "atoms": [ 163, 235 ], "order": 1 },
        { "atoms": [ 163, 228 ], "order": 1 },
        { "atoms": [ 162, 170 ], "order": 1 },
        { "atoms": [ 162, 154 ], "order": 1 },
        { "atoms": [ 162, 235 ], "order": 1 },
        { "atoms": [ 162, 234 ], "order": 1 },
        { "atoms": [ 153, 145 ], "order": 1 },
        { "atoms": [ 153, 152 ], "order": 1 },
        { "atoms": [ 153, 154 ], "order": 1 },
        { "atoms": [ 153, 226 ], "order": 1 },
        { "atoms": [ 153, 217 ], "order": 1 },
        { "atoms": [ 148, 156 ], "order": 1 },
        { "atoms": [ 148, 140 ], "order": 1 },
        { "atoms": [ 148, 147 ], "order": 1 },
        { "atoms": [ 148, 221 ], "order": 1 },
        { "atoms": [ 148, 212 ], "order": 1 },
        { "atoms": [ 171, 172 ], "order": 1 },
        { "atoms": [ 171, 179 ], "order": 1 },
        { "atoms": [ 171, 235 ], "order": 1 },
        { "atoms": [ 171, 243 ], "order": 1 },
        { "atoms": [ 171, 236 ], "order": 1 },
        { "atoms": [ 145, 137 ], "order": 1 },
        { "atoms": [ 145, 146 ], "order": 1 },
        { "atoms": [ 145, 144 ], "order": 1 },
        { "atoms": [ 145, 209 ], "order": 1 },
        { "atoms": [ 145, 218 ], "order": 1 },
        { "atoms": [ 138, 137 ], "order": 1 },
        { "atoms": [ 138, 146 ], "order": 1 },
        { "atoms": [ 138, 130 ], "order": 1 },
        { "atoms": [ 138, 139 ], "order": 1 },
        { "atoms": [ 138, 203 ], "order": 1 },
        { "atoms": [ 138, 210 ], "order": 1 },
        { "atoms": [ 137, 129 ], "order": 1 },
        { "atoms": [ 137, 136 ], "order": 1 },
        { "atoms": [ 137, 210 ], "order": 1 },
        { "atoms": [ 137, 201 ], "order": 1 },
        { "atoms": [ 172, 173 ], "order": 1 },
        { "atoms": [ 172, 164 ], "order": 1 },
        { "atoms": [ 172, 180 ], "order": 1 },
        { "atoms": [ 172, 245 ], "order": 1 },
        { "atoms": [ 172, 236 ], "order": 1 },
        { "atoms": [ 146, 154 ], "order": 1 },
        { "atoms": [ 146, 147 ], "order": 1 },
        { "atoms": [ 146, 211 ], "order": 1 },
        { "atoms": [ 146, 218 ], "order": 1 },
        { "atoms": [ 129, 130 ], "order": 1 },
        { "atoms": [ 129, 128 ], "order": 1 },
        { "atoms": [ 129, 193 ], "order": 1 },
        { "atoms": [ 129, 202 ], "order": 1 },
        { "atoms": [ 136, 128 ], "order": 1 },
        { "atoms": [ 136, 144 ], "order": 1 },
        { "atoms": [ 136, 208 ], "order": 1 },
        { "atoms": [ 136, 201 ], "order": 1 },
        { "atoms": [ 166, 174 ], "order": 1 },
        { "atoms": [ 166, 165 ], "order": 1 },
        { "atoms": [ 166, 167 ], "order": 1 },
        { "atoms": [ 166, 158 ], "order": 1 },
        { "atoms": [ 166, 239 ], "order": 1 },
        { "atoms": [ 166, 230 ], "order": 1 },
        { "atoms": [ 160, 152 ], "order": 1 },
        { "atoms": [ 160, 168 ], "order": 1 },
        { "atoms": [ 160, 225 ], "order": 1 },
        { "atoms": [ 160, 232 ], "order": 1 },
        { "atoms": [ 133, 132 ], "order": 1 },
        { "atoms": [ 133, 134 ], "order": 1 },
        { "atoms": [ 133, 198 ], "order": 1 },
        { "atoms": [ 133, 205 ], "order": 1 },
        { "atoms": [ 174, 173 ], "order": 1 },
        { "atoms": [ 174, 182 ], "order": 1 },
        { "atoms": [ 174, 175 ], "order": 1 },
        { "atoms": [ 174, 247 ], "order": 1 },
        { "atoms": [ 174, 238 ], "order": 1 },
        { "atoms": [ 156, 164 ], "order": 1 },
        { "atoms": [ 156, 155 ], "order": 1 },
        { "atoms": [ 156, 157 ], "order": 1 },
        { "atoms": [ 156, 220 ], "order": 1 },
        { "atoms": [ 156, 229 ], "order": 1 },
        { "atoms": [ 173, 181 ], "order": 1 },
        { "atoms": [ 173, 165 ], "order": 1 },
        { "atoms": [ 173, 238 ], "order": 1 },
        { "atoms": [ 173, 245 ], "order": 1 },
        { "atoms": [ 132, 131 ], "order": 1 },
        { "atoms": [ 132, 140 ], "order": 1 },
        { "atoms": [ 132, 205 ], "order": 1 },
        { "atoms": [ 132, 196 ], "order": 1 },
        { "atoms": [ 134, 142 ], "order": 1 },
        { "atoms": [ 134, 135 ], "order": 1 },
        { "atoms": [ 134, 207 ], "order": 1 },
        { "atoms": [ 134, 198 ], "order": 1 },
        { "atoms": [ 142, 150 ], "order": 1 },
        { "atoms": [ 142, 143 ], "order": 1 },
        { "atoms": [ 142, 215 ], "order": 1 },
        { "atoms": [ 142, 206 ], "order": 1 },
        { "atoms": [ 164, 165 ], "order": 1 },
        { "atoms": [ 164, 228 ], "order": 1 },
        { "atoms": [ 164, 237 ], "order": 1 },
        { "atoms": [ 181, 189 ], "order": 1 },
        { "atoms": [ 181, 180 ], "order": 1 },
        { "atoms": [ 181, 182 ], "order": 1 },
        { "atoms": [ 181, 246 ], "order": 1 },
        { "atoms": [ 181, 253 ], "order": 1 },
        { "atoms": [ 186, 178 ], "order": 1 },
        { "atoms": [ 186, 185 ], "order": 1 },
        { "atoms": [ 186, 187 ], "order": 1 },
        { "atoms": [ 186, 251 ], "order": 1 },
        { "atoms": [ 186, 250 ], "order": 1 },
        { "atoms": [ 178, 170 ], "order": 1 },
        { "atoms": [ 178, 179 ], "order": 1 },
        { "atoms": [ 178, 177 ], "order": 1 },
        { "atoms": [ 178, 243 ], "order": 1 },
        { "atoms": [ 178, 250 ], "order": 1 },
        { "atoms": [ 130, 131 ], "order": 1 },
        { "atoms": [ 130, 203 ], "order": 1 },
        { "atoms": [ 130, 195 ], "order": 1 },
        { "atoms": [ 130, 202 ], "order": 1 },
        { "atoms": [ 128, 200 ], "order": 1 },
        { "atoms": [ 128, 193 ], "order": 1 },
        { "atoms": [ 152, 144 ], "order": 1 },
        { "atoms": [ 152, 224 ], "order": 1 },
        { "atoms": [ 152, 217 ], "order": 1 },
        { "atoms": [ 165, 157 ], "order": 1 },
        { "atoms": [ 165, 230 ], "order": 1 },
        { "atoms": [ 165, 237 ], "order": 1 },
        { "atoms": [ 155, 154 ], "order": 1 },
        { "atoms": [ 155, 147 ], "order": 1 },
        { "atoms": [ 155, 220 ], "order": 1 },
        { "atoms": [ 155, 227 ], "order": 1 },
        { "atoms": [ 189, 190 ], "order": 1 },
        { "atoms": [ 189, 188 ], "order": 1 },
        { "atoms": [ 189, 254 ], "order": 1 },
        { "atoms": [ 144, 209 ], "order": 1 },
        { "atoms": [ 144, 216 ], "order": 1 },
        { "atoms": [ 170, 169 ], "order": 1 },
        { "atoms": [ 170, 235 ], "order": 1 },
        { "atoms": [ 170, 243 ], "order": 1 },
        { "atoms": [ 139, 131 ], "order": 1 },
        { "atoms": [ 139, 140 ], "order": 1 },
        { "atoms": [ 139, 147 ], "order": 1 },
        { "atoms": [ 139, 204 ], "order": 1 },
        { "atoms": [ 139, 211 ], "order": 1 },
        { "atoms": [ 185, 184 ], "order": 1 },
        { "atoms": [ 185, 177 ], "order": 1 },
        { "atoms": [ 185, 249 ], "order": 1 },
        { "atoms": [ 179, 180 ], "order": 1 },
        { "atoms": [ 179, 187 ], "order": 1 },
        { "atoms": [ 179, 251 ], "order": 1 },
        { "atoms": [ 179, 244 ], "order": 1 },
        { "atoms": [ 131, 204 ], "order": 1 },
        { "atoms": [ 131, 203 ], "order": 1 },
        { "atoms": [ 131, 195 ], "order": 1 },
        { "atoms": [ 157, 158 ], "order": 1 },
        { "atoms": [ 157, 229 ], "order": 1 },
        { "atoms": [ 157, 222 ], "order": 1 },
        { "atoms": [ 190, 182 ], "order": 1 },
        { "atoms": [ 190, 191 ], "order": 1 },
        { "atoms": [ 190, 255 ], "order": 1 },
        { "atoms": [ 190, 254 ], "order": 1 },
        { "atoms": [ 176, 168 ], "order": 1 },
        { "atoms": [ 176, 184 ], "order": 1 },
        { "atoms": [ 176, 177 ], "order": 1 },
        { "atoms": [ 176, 248 ], "order": 1 },
        { "atoms": [ 176, 241 ], "order": 1 },
        { "atoms": [ 154, 226 ], "order": 1 },
        { "atoms": [ 154, 219 ], "order": 1 },
        { "atoms": [ 140, 204 ], "order": 1 },
        { "atoms": [ 140, 213 ], "order": 1 },
        { "atoms": [ 180, 188 ], "order": 1 },
        { "atoms": [ 180, 253 ], "order": 1 },
        { "atoms": [ 180, 244 ], "order": 1 },
        { "atoms": [ 168, 169 ], "order": 1 },
        { "atoms": [ 168, 233 ], "order": 1 },
        { "atoms": [ 168, 240 ], "order": 1 },
        { "atoms": [ 188, 187 ], "order": 1 },
        { "atoms": [ 188, 252 ], "order": 1 },
        { "atoms": [ 188, 253 ], "order": 1 },
        { "atoms": [ 182, 183 ], "order": 1 },
        { "atoms": [ 182, 246 ], "order": 1 },
        { "atoms": [ 182, 255 ], "order": 1 },
        { "atoms": [ 184, 249 ], "order": 1 },
        { "atoms": [ 184, 248 ], "order": 1 },
        { "atoms": [ 147, 219 ], "order": 1 },
        { "atoms": [ 147, 212 ], "order": 1 },
        { "atoms": [ 150, 158 ], "order": 1 },
        { "atoms": [ 150, 151 ], "order": 1 },
        { "atoms": [ 150, 223 ], "order": 1 },
        { "atoms": [ 150, 214 ], "order": 1 },
        { "atoms": [ 169, 177 ], "order": 1 },
        { "atoms": [ 169, 233 ], "order": 1 },
        { "atoms": [ 169, 242 ], "order": 1 },
        { "atoms": [ 187, 251 ], "order": 1 },
        { "atoms": [ 187, 252 ], "order": 1 },
        { "atoms": [ 135, 143 ], "order": 1 },
        { "atoms": [ 135, 207 ], "order": 1 },
        { "atoms": [ 135, 199 ], "order": 1 },
        { "atoms": [ 175, 167 ], "order": 1 },
        { "atoms": [ 175, 183 ], "order": 1 },
        { "atoms": [ 175, 239 ], "order": 1 },
        { "atoms": [ 175, 247 ], "order": 1 },
        { "atoms": [ 143, 151 ], "order": 1 },
        { "atoms": [ 143, 207 ], "order": 1 },
        { "atoms": [ 143, 215 ], "order": 1 },
        { "atoms": [ 191, 183 ], "order": 1 },
        { "atoms": [ 191, 255 ], "order": 1 },
        { "atoms": [ 167, 159 ], "order": 1 },
        { "atoms": [ 167, 239 ], "order": 1 },
        { "atoms": [ 167, 231 ], "order": 1 },
        { "atoms": [ 158, 159 ], "order": 1 },
        { "atoms": [ 158, 231 ], "order": 1 },
        { "atoms": [ 158, 222 ], "order": 1 },
        { "atoms": [ 159, 151 ], "order": 1 },
        { "atoms": [ 159, 231 ], "order": 1 },
        { "atoms": [ 159, 223 ], "order": 1 },
        { "atoms": [ 177, 250 ], "order": 1 },
        { "atoms": [ 177, 241 ], "order": 1 },
        { "atoms": [ 151, 215 ], "order": 1 },
        { "atoms": [ 151, 223 ], "order": 1 },
        { "atoms": [ 183, 247 ], "order": 1 },
        { "atoms": [ 183, 255 ], "order": 1 },
        { "atoms": [ 235, 227 ], "order": 1 },
        { "atoms": [ 235, 265 ], "order": 1 },
        { "atoms": [ 226, 234 ], "order": 1 },
        { "atoms": [ 226, 225 ], "order": 1 },
        { "atoms": [ 226, 218 ], "order": 1 },
        { "atoms": [ 226, 260 ], "order": 1 },
        { "atoms": [ 204, 212 ], "order": 1 },
        { "atoms": [ 204, 196 ], "order": 1 },
        { "atoms": [ 204, 287 ], "order": 1 },
        { "atoms": [ 234, 233 ], "order": 1 },
        { "atoms": [ 234, 242 ], "order": 1 },
        { "atoms": [ 234, 273 ], "order": 1 },
        { "atoms": [ 221, 213 ], "order": 1 },
        { "atoms": [ 221, 220 ], "order": 1 },
        { "atoms": [ 221, 229 ], "order": 1 },
        { "atoms": [ 221, 222 ], "order": 1 },
        { "atoms": [ 203, 195 ], "order": 1 },
        { "atoms": [ 203, 202 ], "order": 1 },
        { "atoms": [ 203, 211 ], "order": 1 },
        { "atoms": [ 251, 243 ], "order": 1 },
        { "atoms": [ 251, 252 ], "order": 1 },
        { "atoms": [ 251, 250 ], "order": 1 },
        { "atoms": [ 195, 194 ], "order": 1 },
        { "atoms": [ 195, 196 ], "order": 1 },
        { "atoms": [ 213, 214 ], "order": 1 },
        { "atoms": [ 213, 205 ], "order": 1 },
        { "atoms": [ 213, 281 ], "order": 1 },
        { "atoms": [ 243, 244 ], "order": 1 },
        { "atoms": [ 243, 269 ], "order": 1 },
        { "atoms": [ 219, 211 ], "order": 1 },
        { "atoms": [ 219, 218 ], "order": 1 },
        { "atoms": [ 219, 227 ], "order": 1 },
        { "atoms": [ 219, 271 ], "order": 1 },
        { "atoms": [ 225, 224 ], "order": 1 },
        { "atoms": [ 225, 233 ], "order": 1 },
        { "atoms": [ 225, 217 ], "order": 1 },
        { "atoms": [ 210, 209 ], "order": 1 },
        { "atoms": [ 210, 202 ], "order": 1 },
        { "atoms": [ 210, 211 ], "order": 1 },
        { "atoms": [ 210, 218 ], "order": 1 },
        { "atoms": [ 239, 247 ], "order": 1 },
        { "atoms": [ 239, 238 ], "order": 1 },
        { "atoms": [ 239, 231 ], "order": 1 },
        { "atoms": [ 194, 193 ], "order": 1 },
        { "atoms": [ 194, 202 ], "order": 1 },
        { "atoms": [ 200, 208 ], "order": 1 },
        { "atoms": [ 200, 201 ], "order": 1 },
        { "atoms": [ 200, 192 ], "order": 1 },
        { "atoms": [ 252, 253 ], "order": 1 },
        { "atoms": [ 252, 244 ], "order": 1 },
        { "atoms": [ 208, 209 ], "order": 1 },
        { "atoms": [ 208, 216 ], "order": 1 },
        { "atoms": [ 224, 216 ], "order": 1 },
        { "atoms": [ 224, 232 ], "order": 1 },
        { "atoms": [ 247, 246 ], "order": 1 },
        { "atoms": [ 247, 255 ], "order": 1 },
        { "atoms": [ 238, 246 ], "order": 1 },
        { "atoms": [ 238, 230 ], "order": 1 },
        { "atoms": [ 238, 237 ], "order": 1 },
        { "atoms": [ 250, 249 ], "order": 1 },
        { "atoms": [ 250, 242 ], "order": 1 },
        { "atoms": [ 209, 201 ], "order": 1 },
        { "atoms": [ 209, 217 ], "order": 1 },
        { "atoms": [ 228, 220 ], "order": 1 },
        { "atoms": [ 228, 236 ], "order": 1 },
        { "atoms": [ 228, 227 ], "order": 1 },
        { "atoms": [ 228, 229 ], "order": 1 },
        { "atoms": [ 201, 193 ], "order": 1 },
        { "atoms": [ 201, 202 ], "order": 1 },
        { "atoms": [ 231, 230 ], "order": 1 },
        { "atoms": [ 231, 223 ], "order": 1 },
        { "atoms": [ 216, 217 ], "order": 1 },
        { "atoms": [ 192, 193 ], "order": 1 },
        { "atoms": [ 246, 245 ], "order": 1 },
        { "atoms": [ 246, 254 ], "order": 1 },
        { "atoms": [ 230, 229 ], "order": 1 },
        { "atoms": [ 230, 222 ], "order": 1 },
        { "atoms": [ 207, 199 ], "order": 1 },
        { "atoms": [ 207, 215 ], "order": 1 },
        { "atoms": [ 207, 206 ], "order": 1 },
        { "atoms": [ 199, 198 ], "order": 1 },
        { "atoms": [ 215, 223 ], "order": 1 },
        { "atoms": [ 215, 214 ], "order": 1 },
        { "atoms": [ 245, 253 ], "order": 1 },
        { "atoms": [ 245, 237 ], "order": 1 },
        { "atoms": [ 245, 244 ], "order": 1 },
        { "atoms": [ 220, 212 ], "order": 1 },
        { "atoms": [ 220, 290 ], "order": 1 },
        { "atoms": [ 255, 254 ], "order": 1 },
        { "atoms": [ 233, 232 ], "order": 1 },
        { "atoms": [ 233, 241 ], "order": 1 },
        { "atoms": [ 223, 222 ], "order": 1 },
        { "atoms": [ 253, 254 ], "order": 1 },
        { "atoms": [ 237, 236 ], "order": 1 },
        { "atoms": [ 237, 229 ], "order": 1 },
        { "atoms": [ 249, 248 ], "order": 1 },
        { "atoms": [ 249, 241 ], "order": 1 },
        { "atoms": [ 232, 240 ], "order": 1 },
        { "atoms": [ 206, 214 ], "order": 1 },
        { "atoms": [ 206, 198 ], "order": 1 },
        { "atoms": [ 206, 205 ], "order": 1 },
        { "atoms": [ 214, 222 ], "order": 1 },
        { "atoms": [ 197, 198 ], "order": 1 },
        { "atoms": [ 197, 205 ], "order": 1 },
        { "atoms": [ 197, 196 ], "order": 1 },
        { "atoms": [ 244, 236 ], "order": 1 },
        { "atoms": [ 248, 240 ], "order": 1 },
        { "atoms": [ 240, 241 ], "order": 1 },
        { "atoms": [ 211, 289 ], "order": 1 },
        { "atoms": [ 218, 217 ], "order": 1 },
        { "atoms": [ 205, 283 ], "order": 1 },
        { "atoms": [ 241, 242 ], "order": 1 },
        { "atoms": [ 227, 264 ], "order": 1 },
        { "atoms": [ 227, 271 ], "order": 1 },
        { "atoms": [ 212, 289 ], "order": 1 },
        { "atoms": [ 242, 259 ], "order": 1 },
        { "atoms": [ 264, 265 ], "order": 1 },
        { "atoms": [ 264, 263 ], "order": 1 },
        { "atoms": [ 289, 288 ], "order": 1 },
        { "atoms": [ 289, 310 ], "order": 1 },
        { "atoms": [ 259, 270 ], "order": 1 },
        { "atoms": [ 259, 273 ], "order": 1 },
        { "atoms": [ 271, 262 ], "order": 1 },
        { "atoms": [ 271, 272 ], "order": 1 },
        { "atoms": [ 265, 270 ], "order": 1 },
        { "atoms": [ 265, 266 ], "order": 1 },
        { "atoms": [ 270, 269 ], "order": 1 },
        { "atoms": [ 281, 282 ], "order": 1 },
        { "atoms": [ 281, 280 ], "order": 2 },
        { "atoms": [ 263, 273 ], "order": 1 },
        { "atoms": [ 263, 260 ], "order": 1 },
        { "atoms": [ 273, 301 ], "order": 1 },
        { "atoms": [ 266, 294 ], "order": 1 },
        { "atoms": [ 266, 267 ], "order": 2 },
        { "atoms": [ 260, 262 ], "order": 1 },
        { "atoms": [ 260, 261 ], "order": 1 },
        { "atoms": [ 262, 257 ], "order": 1 },
        { "atoms": [ 269, 268 ], "order": 1 },
        { "atoms": [ 269, 297 ], "order": 1 },
        { "atoms": [ 288, 287 ], "order": 1 },
        { "atoms": [ 287, 282 ], "order": 1 },
        { "atoms": [ 287, 286 ], "order": 1 },
        { "atoms": [ 282, 283 ], "order": 1 },
        { "atoms": [ 257, 298 ], "order": 1 },
        { "atoms": [ 257, 256 ], "order": 2 },
        { "atoms": [ 290, 291 ], "order": 1 },
        { "atoms": [ 290, 274 ], "order": 1 },
        { "atoms": [ 290, 311 ], "order": 1 },
        { "atoms": [ 267, 268 ], "order": 1 },
        { "atoms": [ 267, 295 ], "order": 1 },
        { "atoms": [ 268, 296 ], "order": 1 },
        { "atoms": [ 275, 280 ], "order": 2 },
        { "atoms": [ 275, 274 ], "order": 1 },
        { "atoms": [ 275, 276 ], "order": 1 },
        { "atoms": [ 261, 293 ], "order": 1 },
        { "atoms": [ 261, 258 ], "order": 2 },
        { "atoms": [ 272, 291 ], "order": 1 },
        { "atoms": [ 291, 300 ], "order": 1 },
        { "atoms": [ 283, 284 ], "order": 1 },
        { "atoms": [ 283, 303 ], "order": 1 },
        { "atoms": [ 286, 308 ], "order": 1 },
        { "atoms": [ 286, 285 ], "order": 2 },
        { "atoms": [ 274, 279 ], "order": 1 },
        { "atoms": [ 279, 278 ], "order": 2 },
        { "atoms": [ 279, 307 ], "order": 1 },
        { "atoms": [ 276, 304 ], "order": 1 },
        { "atoms": [ 276, 277 ], "order": 2 },
        { "atoms": [ 285, 284 ], "order": 1 },
        { "atoms": [ 285, 302 ], "order": 1 },
        { "atoms": [ 284, 309 ], "order": 1 },
        { "atoms": [ 256, 258 ], "order": 1 },
        { "atoms": [ 256, 292 ], "order": 1 },
        { "atoms": [ 258, 299 ], "order": 1 },
        { "atoms": [ 277, 278 ], "order": 1 },
        { "atoms": [ 277, 305 ], "order": 1 },
        { "atoms": [ 278, 306 ], "order": 1 }
    ]
}